bitcoinlibdbfix/__init__.py
bitcoinlibdbfix/cli.py
bitcoinlibdbfix/database.py
bitcoinlibdbfix/init.py
bitcoinlibdbfix/installer.py
bitcoinlibdbfix/utils.py
bitcoinlibdbfix/wallet.py
bitcoinlibdbfix-0.4.14.dist-info/LICENSE
bitcoinlibdbfix-0.4.14.dist-info/METADATA
bitcoinlibdbfix-0.4.14.dist-info/WHEEL
bitcoinlibdbfix-0.4.14.dist-info/entry_points.txt
bitcoinlibdbfix-0.4.14.dist-info/RECORD
