Metadata-Version: 2.3
Name: bitcoinlibdbfix
Version: 0.4.14
Summary: Command Line Wallet for Bitcoin with database fixes and CLI replacement
License: MIT
Keywords: bitcoin,wallet,cli,cryptocurrency
Author: Gordon Lawson
Author-email: gordonlawson@gmail.com
Requires-Python: >=3.8
Classifier: License :: OSI Approved :: MIT License
Classifier: Programming Language :: Python :: 3
Classifier: Programming Language :: Python :: 3.8
Classifier: Programming Language :: Python :: 3.9
Classifier: Programming Language :: Python :: 3.10
Classifier: Programming Language :: Python :: 3.11
Classifier: Programming Language :: Python :: 3.12
Classifier: Programming Language :: Python :: 3.13
Requires-Dist: bitcoinlib (>=0.6.0)
Requires-Dist: click (>=8.1.3,<9.0.0)
Requires-Dist: rich (>=13.3.2,<14.0.0)
Requires-Dist: shutilwhich (>=1.1.0,<2.0.0)
Project-URL: Homepage, https://github.com/gordonxdev/bitcoinlibdbfix
Project-URL: Repository, https://github.com/gordonxdev/bitcoinlibdbfix
